embedding/__init__.py
embedding/cli.py
embedding/constants.py
embedding/main.py
embedding/migration_runner.py
embedding/plugin.py
embedding/schema.py
embedding/tools.py
local_ai_utils_embedding-0.0.1.dist-info/licenses/LICENSE
local_ai_utils_embedding-0.0.1.dist-info/METADATA
local_ai_utils_embedding-0.0.1.dist-info/WHEEL
local_ai_utils_embedding-0.0.1.dist-info/entry_points.txt
local_ai_utils_embedding-0.0.1.dist-info/top_level.txt
local_ai_utils_embedding-0.0.1.dist-info/RECORD
